youtube_wrapper/__init__.py
youtube_wrapper/combined.py
youtube_wrapper/data_api.py
youtube_wrapper/transcript_api.py
youtube_wrapper-0.1.0.dist-info/LICENSE
youtube_wrapper-0.1.0.dist-info/METADATA
youtube_wrapper-0.1.0.dist-info/WHEEL
youtube_wrapper-0.1.0.dist-info/top_level.txt
youtube_wrapper-0.1.0.dist-info/RECORD
