Metadata-Version: 2.1
Name: youtube-wrapper
Version: 0.1.0
Summary: A wrapper for YouTube Data API and YouTube Transcript API
Home-page: https://github.com/yourusername/youtube_wrapper
Author: Your Name
Author-email: your.email@example.com
License: UNKNOWN
Platform: UNKNOWN
License-File: LICENSE
Requires-Dist: google-api-python-client
Requires-Dist: requests
